TOPSIS_Raman_101803225/__init__.py
TOPSIS_Raman_101803225-0.0.2.dist-info/LICENSE.txt
TOPSIS_Raman_101803225-0.0.2.dist-info/METADATA
TOPSIS_Raman_101803225-0.0.2.dist-info/WHEEL
TOPSIS_Raman_101803225-0.0.2.dist-info/entry_points.txt
TOPSIS_Raman_101803225-0.0.2.dist-info/top_level.txt
TOPSIS_Raman_101803225-0.0.2.dist-info/RECORD
