Metadata-Version: 2.1
Name: TOPSIS-Raman-101803225
Version: 0.0.2
Summary: adding number
Home-page: UNKNOWN
Author: Ramandeep Singh
Author-email: rsingh1_be18@thapar.edu
License: UNKNOWN
Platform: UNKNOWN
Classifier: Programming Language :: Python :: 3
Classifier: License :: OSI Approved :: MIT License
Classifier: Operating System :: OS Independent
Requires-Dist: pandas
